ColorHarmony/__init__.py
ColorHarmony/colorHarmony.py
ColorHarmony/utils.py
color_harmony-1.0.1.dist-info/LICENSE
color_harmony-1.0.1.dist-info/METADATA
color_harmony-1.0.1.dist-info/WHEEL
color_harmony-1.0.1.dist-info/entry_points.txt
color_harmony-1.0.1.dist-info/top_level.txt
color_harmony-1.0.1.dist-info/RECORD
