Metadata-Version: 2.1
Name: color-harmony
Version: 1.0.1
Summary: A Python package to get color harmonies of a given image.
Home-page: https://github.com/profnote/ColorHarmony
Author: Niti Wattanasirichaigoon
Author-email: niti.wattanasirichaigoon@gmail.com
License: MIT
Platform: UNKNOWN
Classifier: License :: OSI Approved :: MIT License
Classifier: Programming Language :: Python :: 3
Classifier: Programming Language :: Python :: 3.7
Requires-Dist: pillow
Requires-Dist: scikit-learn
Requires-Dist: matplotlib
